README.rst
setup.py
src/queue_helpers/__init__.py
src/queue_helpers/queue_helpers.py
src/queue_helpers.egg-info/PKG-INFO
src/queue_helpers.egg-info/SOURCES.txt
src/queue_helpers.egg-info/dependency_links.txt
src/queue_helpers.egg-info/requires.txt
src/queue_helpers.egg-info/top_level.txt