Metadata-Version: 2.1
Name: queue-helpers
Version: 0.1.4
Summary: A helper to manage Rabbit queues.
Home-page: https://github.com/ChamRun/queue_helpers
Author: Gradient Data Processing
Author-email: info@gradientdp.com
License: UNKNOWN
Project-URL: Organization, https://gradientdp.com/
Keywords: queue,pika,rabbit
Platform: UNKNOWN
Requires-Python: >=3.7
